LICENSE
MANIFEST.in
README.md
main.py
rdm_env_setting.yaml
requirements.txt
setup.py
brdm/BaseRefData.py
brdm/GreenGeneData.py
brdm/NcbiBlastData.py
brdm/NcbiData.py
brdm/NcbiSubsetData.py
brdm/NcbiTaxonomyData.py
brdm/NcbiWholeGenome.py
brdm/RefDataInterface.py
brdm/SilvaData.py
brdm/UniteData.py
brdm/__init__.py
brdm/brdm_root.py
brdm/config.yaml.sample
reference_data_manager.egg-info/PKG-INFO
reference_data_manager.egg-info/SOURCES.txt
reference_data_manager.egg-info/dependency_links.txt
reference_data_manager.egg-info/entry_points.txt
reference_data_manager.egg-info/top_level.txt