Metadata-Version: 1.1
Name: reference-data-manager
Version: 0.5
Summary: Bioinformatics Reference Data Manager is an application
Home-page: https://github.com/AAFC-BICoE/reference-data-manager
Author: Chunfang Zheng, Oksana Korol
Author-email: aafc.bice-ceib.aac@canada.ca
License: MIT License
